[
    {
        "id":  "movement_primary_tier1",
        "category":  "primary",
        "soundEffect":  "movement_primary_sound",
        "subclass":  "Default",
        "visualEffect":  "movement_primary_tier1",
        "tier":  "TIER_1",
        "energyCost":  6,
        "damage":  null,
        "name":  "Movement Primary Tier 1",
        "description":  "A primary ability for movement particles at tier 1",
        "cooldown":  11,
        "range":  6,
        "heal":  null
    },
    {
        "range":  7,
        "id":  "movement_secondary_tier1",
        "soundEffect":  "movement_secondary_sound",
        "subclass":  "Default",
        "category":  "secondary",
        "description":  "A secondary ability for movement particles at tier 1",
        "name":  "Movement Secondary Tier 1",
        "visualEffect":  "movement_secondary_tier1",
        "tier":  "TIER_1",
        "duration":  4,
        "energyCost":  8,
        "cooldown":  13
    },
    {
        "range":  9,
        "id":  "movement_unique_tier1",
        "soundEffect":  "movement_unique_sound",
        "subclass":  "Default",
        "category":  "unique",
        "description":  "A unique ability for movement particles at tier 1",
        "name":  "Movement Unique Tier 1",
        "visualEffect":  "movement_unique_tier1",
        "tier":  "TIER_1",
        "area":  6,
        "energyCost":  12,
        "cooldown":  17
    },
    {
        "range":  8,
        "id":  "movement_cc_tier1",
        "soundEffect":  "movement_cc_sound",
        "subclass":  "Default",
        "category":  "crowdControl",
        "description":  "A crowd control ability for movement particles at tier 1",
        "name":  "Movement Crowd Control Tier 1",
        "visualEffect":  "movement_cc_tier1",
        "tier":  "TIER_1",
        "duration":  2.5,
        "energyCost":  9,
        "cooldown":  20
    }
]
